{
  "immediateReplace": true,
  "suggester": true,
  "historyPriority": true,
  "historyLimit": 100,
  "history": [
    ":white_check_mark:",
    ":negative_squared_cross_mark:",
    ":greece:",
    ":es:",
    ":colombia:",
    ":vietnam:",
    ":malaysia:",
    ":argentina:",
    ":australia:",
    ":kr:",
    ":singapore:",
    ":finland:",
    ":tr:",
    ":cn:",
    ":new_zealand:",
    ":pregnant_woman:",
    ":hamburger:",
    ":football:",
    ":cityscape:",
    ":gun:",
    ":eagle:",
    ":us:",
    ":canada:",
    ":chile:",
    ":jp:",
    ":taiwan:",
    ":jordan:",
    ":hong_kong:",
    ":norway:",
    ":estonia:",
    ":czech_republic:",
    ":aries:",
    ":sweden:",
    ":romania:",
    ":portugal:",
    ":poland:",
    ":it:",
    ":ireland:",
    ":uk:",
    ":fr:",
    ":abacus:"
  ]
}